{
  "multipart": [
    {
      "apply": {
        "model": "cozyfoods:block/menu_standing"
      },
      "when": {
        "facing": "north"
      }
    },
    {
      "apply": {
        "model": "cozyfoods:block/menu_standing", "y": 90
      },
      "when": {
        "facing": "east"
      }
    },
    {
      "apply": {
        "model": "cozyfoods:block/menu_standing", "y": 180
      },
      "when": {
        "facing": "south"
      }
    },
    {
      "apply": {
        "model": "cozyfoods:block/menu_standing", "y": 270
      },
      "when": {
        "facing": "west"
      }
    }
  ]
}
